swapportunity/__init__.py
swapportunity/main.py
swapportunity-0.0.22.dist-info/LICENSE
swapportunity-0.0.22.dist-info/METADATA
swapportunity-0.0.22.dist-info/WHEEL
swapportunity-0.0.22.dist-info/top_level.txt
swapportunity-0.0.22.dist-info/RECORD
