Metadata-Version: 2.1
Name: swapportunity
Version: 0.0.22
Summary: A defi swap helper package
Author: MrAniki
Project-URL: Homepage, https://github.com/mraniki/swapportunity
Project-URL: Bug Tracker, https://github.com/mraniki/swapportunity/issues
Classifier: Programming Language :: Python :: 3
Classifier: License :: OSI Approved :: MIT License
Classifier: Operating System :: OS Independent
Requires-Python: >=3.7
License-File: LICENSE
